LaharZ/LaharZ.py
LaharZ/__init__.py
LaharZ-3.0.19.dist-info/LICENSE.txt
LaharZ-3.0.19.dist-info/METADATA
LaharZ-3.0.19.dist-info/WHEEL
LaharZ-3.0.19.dist-info/top_level.txt
LaharZ-3.0.19.dist-info/RECORD
